{"CHN": {"participants": 479, "male": 212, "female": 267, "medal": 125}, "FRA": {"participants": 426, "male": 243, "female": 183, "medal": 82}, "MAR": {"participants": 67, "male": 48, "female": 19, "medal": 1}, "RUS": {"participants": 549, "male": 266, "female": 283, "medal": 140}, "ARG": {"participants": 148, "male": 103, "female": 45, "medal": 19}, "ITA": {"participants": 382, "male": 212, "female": 170, "medal": 68}, "ALG": {"participants": 39, "male": 22, "female": 17, "medal": 1}, "PAK": {"participants": 21, "male": 19, "female": 2, "medal": 0}, "IRI": {"participants": 57, "male": 46, "female": 11, "medal": 12}, "EGY": {"participants": 132, "male": 87, "female": 45, "medal": 2}, "AUS": {"participants": 514, "male": 271, "female": 243, "medal": 114}, "USA": {"participants": 689, "male": 346, "female": 343, "medal": 248}, "CMR": {"participants": 32, "male": 10, "female": 22, "medal": 0}, "IRQ": {"participants": 8, "male": 5, "female": 3, "medal": 0}, "UZB": {"participants": 56, "male": 37, "female": 19, "medal": 3}, "AZE": {"participants": 59, "male": 43, "female": 16, "medal": 10}, "UAE": {"participants": 26, "male": 24, "female": 2, "medal": 0}, "KGZ": {"participants": 15, "male": 12, "female": 3, "medal": 0}, "TJK": {"participants": 16, "male": 13, "female": 3, "medal": 1}, "CAN": {"participants": 354, "male": 146, "female": 208, "medal": 55}, "CUB": {"participants": 118, "male": 70, "female": 48, "medal": 14}, "ESP": {"participants": 339, "male": 203, "female": 136, "medal": 63}, "JPN": {"participants": 399, "male": 199, "female": 200, "medal": 84}, "NGR": {"participants": 58, "male": 30, "female": 28, "medal": 0}, "POR": {"participants": 98, "male": 56, "female": 42, "medal": 2}, "SUI": {"participants": 126, "male": 89, "female": 37, "medal": 4}, "COL": {"participants": 120, "male": 56, "female": 64, "medal": 8}, "ETH": {"participants": 34, "male": 18, "female": 16, "medal": 7}, "JOR": {"participants": 9, "male": 5, "female": 4, "medal": 0}, "PLE": {"participants": 5, "male": 3, "female": 2, "medal": 0}, "KAZ": {"participants": 132, "male": 85, "female": 47, "medal": 13}, "GBR": {"participants": 684, "male": 350, "female": 334, "medal": 126}, "UGA": {"participants": 16, "male": 12, "female": 4, "medal": 1}, "TUN": {"participants": 87, "male": 66, "female": 21, "medal": 3}, "NED": {"participants": 222, "male": 117, "female": 105, "medal": 69}, "MEX": {"participants": 119, "male": 74, "female": 45, "medal": 24}, "VEN": {"participants": 85, "male": 49, "female": 36, "medal": 1}, "POL": {"participants": 256, "male": 145, "female": 111, "medal": 12}, "NIG": {"participants": 6, "male": 4, "female": 2, "medal": 0}, "SKN": {"participants": 7, "male": 7, "female": 0, "medal": 0}, "NZL": {"participants": 204, "male": 110, "female": 94, "medal": 27}, "GER": {"participants": 510, "male": 279, "female": 231, "medal": 94}, "LBR": {"participants": 3, "male": 1, "female": 2, "medal": 0}, "ERI": {"participants": 12, "male": 11, "female": 1, "medal": 0}, "BRA": {"participants": 306, "male": 162, "female": 144, "medal": 59}, "SWE": {"participants": 168, "male": 66, "female": 102, "medal": 22}, "BEL": {"participants": 142, "male": 93, "female": 49, "medal": 3}, "MAS": {"participants": 38, "male": 22, "female": 16, "medal": 2}, "GRE": {"participants": 115, "male": 70, "female": 45, "medal": 3}, "ROU": {"participants": 155, "male": 82, "female": 73, "medal": 16}, "RWA": {"participants": 7, "male": 5, "female": 2, "medal": 0}, "TOG": {"participants": 6, "male": 4, "female": 2, "medal": 0}, "PAR": {"participants": 10, "male": 6, "female": 4, "medal": 0}, "URU": {"participants": 27, "male": 24, "female": 3, "medal": 0}, "COM": {"participants": 3, "male": 1, "female": 2, "medal": 0}, "INA": {"participants": 22, "male": 13, "female": 9, "medal": 2}, "MDV": {"participants": 5, "male": 3, "female": 2, "medal": 0}, "BEN": {"participants": 5, "male": 4, "female": 1, "medal": 0}, "CIV": {"participants": 10, "male": 4, "female": 6, "medal": 0}, "NAM": {"participants": 9, "male": 5, "female": 4, "medal": 0}, "EST": {"participants": 36, "male": 25, "female": 11, "medal": 2}, "TTO": {"participants": 38, "male": 26, "female": 12, "medal": 10}, "LTU": {"participants": 72, "male": 42, "female": 30, "medal": 5}, "UKR": {"participants": 304, "male": 161, "female": 143, "medal": 26}, "VIN": {"participants": 3, "male": 2, "female": 1, "medal": 0}, "TUR": {"participants": 119, "male": 52, "female": 67, "medal": 5}, "CYP": {"participants": 13, "male": 9, "female": 4, "medal": 1}, "KSA": {"participants": 23, "male": 21, "female": 2, "medal": 4}, "KUW": {"participants": 12, "male": 9, "female": 3, "medal": 1}, "QAT": {"participants": 14, "male": 9, "female": 5, "medal": 2}, "BRN": {"participants": 14, "male": 4, "female": 10, "medal": 1}, "YEM": {"participants": 4, "male": 3, "female": 1, "medal": 0}, "OMA": {"participants": 3, "male": 2, "female": 1, "medal": 0}, "SUD": {"participants": 6, "male": 4, "female": 2, "medal": 0}, "FIN": {"participants": 69, "male": 32, "female": 37, "medal": 5}, "FIJ": {"participants": 9, "male": 6, "female": 3, "medal": 0}, "VAN": {"participants": 5, "male": 3, "female": 2, "medal": 0}, "JAM": {"participants": 62, "male": 29, "female": 33, "medal": 25}, "GUA": {"participants": 24, "male": 14, "female": 10, "medal": 1}, "PUR": {"participants": 28, "male": 19, "female": 9, "medal": 2}, "BUL": {"participants": 75, "male": 39, "female": 36, "medal": 2}, "ARM": {"participants": 31, "male": 27, "female": 4, "medal": 3}, "LAT": {"participants": 50, "male": 36, "female": 14, "medal": 3}, "SRB": {"participants": 134, "male": 92, "female": 42, "medal": 16}, "BLR": {"participants": 185, "male": 99, "female": 86, "medal": 23}, "IVB": {"participants": 2, "male": 1, "female": 1, "medal": 0}, "ESA": {"participants": 11, "male": 5, "female": 6, "medal": 0}, "MAD": {"participants": 7, "male": 3, "female": 4, "medal": 0}, "DJI": {"participants": 4, "male": 2, "female": 2, "medal": 0}, "CRO": {"participants": 118, "male": 69, "female": 49, "medal": 35}, "PHI": {"participants": 11, "male": 7, "female": 4, "medal": 0}, "SEY": {"participants": 6, "male": 4, "female": 2, "medal": 0}, "BAR": {"participants": 8, "male": 8, "female": 0, "medal": 0}, "ECU": {"participants": 36, "male": 23, "female": 13, "medal": 0}, "ANG": {"participants": 35, "male": 6, "female": 29, "medal": 0}, "NOR": {"participants": 69, "male": 37, "female": 32, "medal": 17}, "CRC": {"participants": 11, "male": 8, "female": 3, "medal": 0}, "AUT": {"participants": 90, "male": 52, "female": 38, "medal": 0}, "BAH": {"participants": 29, "male": 16, "female": 13, "medal": 4}, "BOT": {"participants": 4, "male": 3, "female": 1, "medal": 1}, "GHA": {"participants": 7, "male": 5, "female": 2, "medal": 0}, "PRK": {"participants": 57, "male": 17, "female": 40, "medal": 6}, "DEN": {"participants": 149, "male": 76, "female": 73, "medal": 16}, "KEN": {"participants": 51, "male": 29, "female": 22, "medal": 11}, "IRL": {"participants": 76, "male": 42, "female": 34, "medal": 5}, "MGL": {"participants": 32, "male": 18, "female": 14, "medal": 5}, "SLO": {"participants": 78, "male": 30, "female": 48, "medal": 5}, "PLW": {"participants": 5, "male": 2, "female": 3, "medal": 0}, "HUN": {"participants": 201, "male": 113, "female": 88, "medal": 26}, "IND": {"participants": 95, "male": 66, "female": 29, "medal": 6}, "CZE": {"participants": 159, "male": 81, "female": 78, "medal": 14}, "RSA": {"participants": 145, "male": 84, "female": 61, "medal": 9}, "CHI": {"participants": 44, "male": 26, "female": 18, "medal": 0}, "THA": {"participants": 43, "male": 22, "female": 21, "medal": 3}, "DOM": {"participants": 36, "male": 15, "female": 21, "medal": 2}, "PER": {"participants": 16, "male": 9, "female": 7, "medal": 0}, "ISL": {"participants": 36, "male": 24, "female": 12, "medal": 0}, "ISR": {"participants": 56, "male": 33, "female": 23, "medal": 0}, "MRI": {"participants": 11, "male": 4, "female": 7, "medal": 0}, "MDA": {"participants": 20, "male": 12, "female": 8, "medal": 2}, "GUM": {"participants": 8, "male": 5, "female": 3, "medal": 0}, "HKG": {"participants": 55, "male": 26, "female": 29, "medal": 1}, "GAB": {"participants": 21, "male": 19, "female": 2, "medal": 1}, "MYA": {"participants": 6, "male": 3, "female": 3, "medal": 0}, "AFG": {"participants": 6, "male": 5, "female": 1, "medal": 1}, "SEN": {"participants": 32, "male": 25, "female": 7, "medal": 0}, "LIB": {"participants": 10, "male": 3, "female": 7, "medal": 0}, "KOR": {"participants": 312, "male": 176, "female": 136, "medal": 61}, "ANT": {"participants": 4, "male": 2, "female": 2, "medal": 0}, "CGO": {"participants": 7, "male": 4, "female": 3, "medal": 0}, "BOL": {"participants": 5, "male": 3, "female": 2, "medal": 0}, "MON": {"participants": 6, "male": 5, "female": 1, "medal": 0}, "SYR": {"participants": 10, "male": 6, "female": 4, "medal": 0}, "MNE": {"participants": 34, "male": 19, "female": 15, "medal": 14}, "GUI": {"participants": 4, "male": 2, "female": 2, "medal": 0}, "SVK": {"participants": 65, "male": 35, "female": 30, "medal": 5}, "GUY": {"participants": 6, "male": 4, "female": 2, "medal": 0}, "TKM": {"participants": 10, "male": 7, "female": 3, "medal": 0}, "LCA": {"participants": 4, "male": 1, "female": 3, "medal": 0}, "ALB": {"participants": 10, "male": 7, "female": 3, "medal": 0}, "HON": {"participants": 25, "male": 22, "female": 3, "medal": 0}, "SAM": {"participants": 9, "male": 6, "female": 3, "medal": 0}, "AND": {"participants": 6, "male": 4, "female": 2, "medal": 0}, "GRN": {"participants": 8, "male": 5, "female": 3, "medal": 1}, "BDI": {"participants": 6, "male": 2, "female": 4, "medal": 0}, "MKD": {"participants": 4, "male": 2, "female": 2, "medal": 0}, "GEO": {"participants": 36, "male": 28, "female": 8, "medal": 7}, "IOA": {"participants": 4, "male": 3, "female": 1, "medal": 0}, "MLT": {"participants": 5, "male": 3, "female": 2, "medal": 0}, "CAF": {"participants": 6, "male": 3, "female": 3, "medal": 0}, "NCA": {"participants": 6, "male": 3, "female": 3, "medal": 0}, "COK": {"participants": 9, "male": 4, "female": 5, "medal": 0}, "BER": {"participants": 8, "male": 5, "female": 3, "medal": 0}, "BAN": {"participants": 7, "male": 6, "female": 1, "medal": 0}, "LUX": {"participants": 11, "male": 7, "female": 4, "medal": 0}, "MOZ": {"participants": 6, "male": 4, "female": 2, "medal": 0}, "MLI": {"participants": 6, "male": 4, "female": 2, "medal": 0}, "PAN": {"participants": 8, "male": 6, "female": 2, "medal": 0}, "CAM": {"participants": 6, "male": 3, "female": 3, "medal": 0}, "TPE": {"participants": 55, "male": 22, "female": 33, "medal": 2}, "SGP": {"participants": 36, "male": 12, "female": 24, "medal": 4}, "BHU": {"participants": 2, "male": 0, "female": 2, "medal": 0}, "ZAM": {"participants": 7, "male": 5, "female": 2, "medal": 0}, "VIE": {"participants": 24, "male": 8, "female": 16, "medal": 0}, "GAM": {"participants": 2, "male": 1, "female": 1, "medal": 0}, "SRI": {"participants": 8, "male": 5, "female": 3, "medal": 0}, "ZIM": {"participants": 9, "male": 4, "female": 5, "medal": 0}, "STP": {"participants": 2, "male": 1, "female": 1, "medal": 0}, "GBS": {"participants": 4, "male": 2, "female": 2, "medal": 0}, "FSM": {"participants": 6, "male": 4, "female": 2, "medal": 0}, "KIR": {"participants": 3, "male": 2, "female": 1, "medal": 0}, "HAI": {"participants": 5, "male": 3, "female": 2, "medal": 0}, "NRU": {"participants": 2, "male": 2, "female": 0, "medal": 0}, "NEP": {"participants": 5, "male": 2, "female": 3, "medal": 0}, "LBA": {"participants": 4, "male": 3, "female": 1, "medal": 0}, "MTN": {"participants": 2, "male": 1, "female": 1, "medal": 0}, "GEQ": {"participants": 2, "male": 1, "female": 1, "medal": 0}, "ASA": {"participants": 4, "male": 3, "female": 1, "medal": 0}, "SOM": {"participants": 2, "male": 1, "female": 1, "medal": 0}, "BIH": {"participants": 8, "male": 6, "female": 2, "medal": 0}, "TGA": {"participants": 3, "male": 2, "female": 1, "medal": 0}, "CAY": {"participants": 7, "male": 7, "female": 0, "medal": 0}, "DMA": {"participants": 2, "male": 1, "female": 1, "medal": 0}, "MHL": {"participants": 4, "male": 2, "female": 2, "medal": 0}, "TAN": {"participants": 6, "male": 4, "female": 2, "medal": 0}, "SMR": {"participants": 4, "male": 1, "female": 3, "medal": 0}, "ISV": {"participants": 9, "male": 4, "female": 5, "medal": 0}, "SWZ": {"participants": 3, "male": 2, "female": 1, "medal": 0}, "LIE": {"participants": 4, "male": 1, "female": 3, "medal": 0}, "ARU": {"participants": 4, "male": 3, "female": 1, "medal": 0}, "LAO": {"participants": 3, "male": 2, "female": 1, "medal": 0}, "PNG": {"participants": 8, "male": 4, "female": 4, "medal": 0}, "COD": {"participants": 4, "male": 3, "female": 1, "medal": 0}, "BUR": {"participants": 5, "male": 2, "female": 3, "medal": 0}, "SOL": {"participants": 4, "male": 2, "female": 2, "medal": 0}, "TUV": {"participants": 3, "male": 2, "female": 1, "medal": 0}, "LES": {"participants": 4, "male": 2, "female": 2, "medal": 0}, "BRU": {"participants": 3, "male": 2, "female": 1, "medal": 0}, "CPV": {"participants": 3, "male": 1, "female": 2, "medal": 0}, "BIZ": {"participants": 3, "male": 2, "female": 1, "medal": 0}, "TLS": {"participants": 2, "male": 1, "female": 1, "medal": 0}, "CHA": {"participants": 2, "male": 0, "female": 2, "medal": 0}, "SUR": {"participants": 5, "male": 3, "female": 2, "medal": 0}, "SLE": {"participants": 2, "male": 1, "female": 1, "medal": 0}, "MAW": {"participants": 3, "male": 1, "female": 2, "medal": 0}}